create_api_django
