Metadata-Version: 1.1
Name: create-api-django
Version: 0.4.0
Summary: Django Rest Framework Boilerplate to easily create APIs
Home-page: https://github.com/matfire/create-api-django
Author: Matteo Gassend
Author-email: mgassend@gmail.com
License: MIT license
Keywords: create_api_django
Platform: UNKNOWN
Classifier: Development Status :: 2 - Pre-Alpha
Classifier: Intended Audience :: Developers
Classifier: License :: OSI Approved :: MIT License
Classifier: Natural Language :: English
Classifier: Programming Language :: Python :: 3.5
Classifier: Programming Language :: Python :: 3.6
Classifier: Programming Language :: Python :: 3.7
